approck_sqlalchemy_utils/__init__.py
approck_sqlalchemy_utils/alembic/__init__.py
approck_sqlalchemy_utils/alembic/humanreadable.py
approck_sqlalchemy_utils/exceptions.py
approck_sqlalchemy_utils/mixins/__init__.py
approck_sqlalchemy_utils/mixins/auto_now.py
approck_sqlalchemy_utils/mocks.py
approck_sqlalchemy_utils/model.py
approck_sqlalchemy_utils/parsers/__init__.py
approck_sqlalchemy_utils/parsers/order_by.py
approck_sqlalchemy_utils/session.py
approck_sqlalchemy_utils/types/__init__.py
approck_sqlalchemy_utils/types/encrypted/__init__.py
approck_sqlalchemy_utils/types/encrypted/encrypted_type.py
approck_sqlalchemy_utils/types/encrypted/padding.py
approck_sqlalchemy_utils/types/json.py
approck_sqlalchemy_utils/types/scalar_coercible.py
approck_sqlalchemy_utils/types/scalar_list.py
approck_sqlalchemy_utils-0.1.4.dist-info/METADATA
approck_sqlalchemy_utils-0.1.4.dist-info/WHEEL
approck_sqlalchemy_utils-0.1.4.dist-info/RECORD
